py_country_info_all/__init__.py
py_country_info_all/data.py
py_country_info_all/py_country_info_all.py
py_country_info_all-0.2.dist-info/METADATA
py_country_info_all-0.2.dist-info/WHEEL
py_country_info_all-0.2.dist-info/top_level.txt
py_country_info_all-0.2.dist-info/RECORD
