Metadata-Version: 2.1
Name: py_country_info_all
Version: 0.2
Summary: A package to retrieve country info including ISO codes, country code, and flags.
Home-page: https://github.com/pabal15522/py_country_info_all.git
Author: SIMPARA Ibrahim
Author-email: ibrahim_simpara@yahoo.com
Classifier: Programming Language :: Python :: 3
Classifier: License :: OSI Approved :: MIT License
Classifier: Operating System :: OS Independent
